AUTHORS.rst
MANIFEST.in
README.rst
pyproject.toml
setup.cfg
setup.py
docs/Makefile
docs/authors.rst
docs/conf.py
docs/contributing.rst
docs/history.rst
docs/index.rst
docs/installation.rst
docs/make.bat
docs/readme.rst
docs/usage.rst
src/deoxys_vis/__init__.py
src/deoxys_vis/performance.py
src/deoxys_vis/results.py
src/deoxys_vis.egg-info/PKG-INFO
src/deoxys_vis.egg-info/SOURCES.txt
src/deoxys_vis.egg-info/dependency_links.txt
src/deoxys_vis.egg-info/requires.txt
src/deoxys_vis.egg-info/top_level.txt
src/deoxys_vis/utils/__init__.py
src/deoxys_vis/utils/data_utils.py
tests/__init__.py