Metadata-Version: 1.1
Name: deoxys-vis
Version: 0.0.1
Summary: Visualize medical images
Home-page: https://github.com/huynhngoc/deoxys-vis
Author: Ngoc Huynh Bao
Author-email: ngoc.huynh.bao@nmbu.no
License: "MIT license",
Keywords: deoxys-vis
Platform: UNKNOWN
Classifier: Intended Audience :: Developers
Classifier: License :: OSI Approved :: MIT License
Classifier: Natural Language :: English
Classifier: Programming Language :: Python :: 3.6
Classifier: Programming Language :: Python :: 3.7
